pysam-stubs/__init__.pyi
pysam-stubs/libcalignedsegment.pyi
pysam-stubs/libcalignmentfile.pyi
pysam-stubs/libcbcf.pyi
pysam-stubs/libcbcftools.pyi
pysam-stubs/libcbgzf.pyi
pysam-stubs/libcfaidx.pyi
pysam-stubs/libchtslib.pyi
pysam-stubs/libcsamfile.pyi
pysam-stubs/libcsamtools.pyi
pysam-stubs/libctabix.pyi
pysam-stubs/libctabixproxies.pyi
pysam-stubs/libcutils.pyi
pysam-stubs/libcvcf.pyi
pysam-stubs/version.pyi
pysam_stubs-0.18.0.0.2.dist-info/METADATA
pysam_stubs-0.18.0.0.2.dist-info/WHEEL
pysam_stubs-0.18.0.0.2.dist-info/top_level.txt
pysam_stubs-0.18.0.0.2.dist-info/RECORD
