Metadata-Version: 2.1
Name: pysam-stubs
Version: 0.18.0.0.2
Summary: UNKNOWN
Home-page: https://github.com/marcelm/pysam-stubs/
Author: Marcel Martin
Author-email: marcel.martin@scilifelab.se
License: CC0
Platform: UNKNOWN
Classifier: License :: CC0 1.0 Universal (CC0 1.0) Public Domain Dedication
Requires-Python: >=3.6
